pyfdev/__init__.py
pyfdev/__main__.py
pyfdev/compiler/__init__.py
pyfdev/compiler/cli.py
pyfdev/compiler/parser.py
pyfdev/compiler/runner.py
pyfdev/compiler/transpiler.py
pyfdev-0.1.7.dist-info/METADATA
pyfdev-0.1.7.dist-info/WHEEL
pyfdev-0.1.7.dist-info/entry_points.txt
pyfdev-0.1.7.dist-info/top_level.txt
pyfdev-0.1.7.dist-info/RECORD
