Metadata-Version: 2.4
Name: pyfdev
Version: 0.1.7
Summary: Pyfdev transpiler and CLI
Author: Priyanshu Rauth
Author-email: raut.priyanshu30@gmail.com
Keywords: pyfdev,transpiler,compiler,cli,python
Classifier: Programming Language :: Python :: 3
Classifier: License :: OSI Approved :: MIT License
Classifier: Operating System :: OS Independent
Requires-Python: >=3.7
Dynamic: author
Dynamic: author-email
Dynamic: classifier
Dynamic: description
Dynamic: description-content-type
Dynamic: keywords
Dynamic: requires-python
Dynamic: summary
